Metadata-Version: 2.1
Name: paho-socket
Version: 0.0.3
Summary: Thin layer built on top of paho-mqtt allowing for connections with unix socket brokers.
Home-page: https://github.com/mgetka/paho-socket
Author: Michał Getka
Author-email: michal.getka@gmail.com
License: UNKNOWN
Keywords: paho unix
Platform: UNKNOWN
Classifier: Development Status :: 4 - Beta
Classifier: Intended Audience :: Developers
Classifier: License :: OSI Approved
Classifier: Operating System :: POSIX
Classifier: Natural Language :: English
Classifier: Programming Language :: Python
Classifier: Programming Language :: Python :: 3.7
Classifier: Programming Language :: Python :: 3.8
Classifier: Programming Language :: Python :: 3.9
Classifier: Topic :: Communications
Classifier: Topic :: Internet
Requires-Python: >=3.7
Provides-Extra: dev
